[{"id": "bitcoin", "name": "Bitcoin", "symbol": "BTC", "rank": "1", "price_usd": "8242.58", "price_btc": "1.0", "24h_volume_usd": "6967450000.0", "market_cap_usd": "141514070028", "available_supply": "17168662.0", "total_supply": "17168662.0", "max_supply": "21000000.0", "percent_change_1h": "0.32", "percent_change_24h": "6.56", "percent_change_7d": "13.64", "last_updated": "1532469385", "price_eur": "7055.07052862", "24h_volume_eur": "5963648657.9", "market_cap_eur": "121126121292"}, {"id": "ethereum", "name": "Ethereum", "symbol": "ETH", "rank": "2", "price_usd": "475.023", "price_btc": "0.0576455", "24h_volume_usd": "2221070000.0", "market_cap_usd": "47928371122.0", "available_supply": "100896948.0", "total_supply": "100896948.0", "max_supply": null, "percent_change_1h": "0.37", "percent_change_24h": "5.09", "percent_change_7d": "-4.74", "last_updated": "1532469415", "price_eur": "406.586380444", "24h_volume_eur": "1901080183.51", "market_cap_eur": "41023325050.0"}, {"id": "ripple", "name": "XRP", "symbol": "XRP", "rank": "3", "price_usd": "0.45406", "price_btc": "0.00005510", "24h_volume_usd": "306622000.0", "market_cap_usd": "17851679239.0", "available_supply": "39315683476.0", "total_supply": "99991900487.0", "max_supply": "100000000000", "percent_change_1h": "0.35", "percent_change_24h": "1.75", "percent_change_7d": "-10.01", "last_updated": "1532469409", "price_eur": "0.3886435223", "24h_volume_eur": "262446932.347", "market_cap_eur": "15279785709.0"}, {"id": "bitcoin-cash", "name": "Bitcoin Cash", "symbol": "BCH", "rank": "4", "price_usd": "853.193", "price_btc": "0.103538", "24h_volume_usd": "872982000.0", "market_cap_usd": "14722058513.0", "available_supply": "17255250.0", "total_supply": "17255250.0", "max_supply": "21000000.0", "percent_change_1h": "0.38", "percent_change_24h": "7.8", "percent_change_7d": "0.82", "last_updated": "1532469395", "price_eur": "730.273384004", "24h_volume_eur": "747211380.444", "market_cap_eur": "12601049809.0"}, {"id": "eos", "name": "EOS", "symbol": "EOS", "rank": "5", "price_usd": "8.46077", "price_btc": "0.00102674", "24h_volume_usd": "974934000.0", "market_cap_usd": "7582114739.0", "available_supply": "896149492.0", "total_supply": "900000000.0", "max_supply": "1000000000.0", "percent_change_1h": "0.16", "percent_change_24h": "6.12", "percent_change_7d": "-2.98", "last_updated": "1532469393", "price_eur": "7.2418258696", "24h_volume_eur": "834475143.796", "market_cap_eur": "6489758575.0"}, {"id": "stellar", "name": "Stellar", "symbol": "XLM", "rank": "6", "price_usd": "0.299571", "price_btc": "0.00003635", "24h_volume_usd": "104132000.0", "market_cap_usd": "5622138567.0", "available_supply": "18767299129.0", "total_supply": "104144920420", "max_supply": null, "percent_change_1h": "0.23", "percent_change_24h": "5.15", "percent_change_7d": "19.41", "last_updated": "1532469383", "price_eur": "0.2564117707", "24h_volume_eur": "89129690.4958", "market_cap_eur": "4812156402.0"}, {"id": "litecoin", "name": "Litecoin", "symbol": "LTC", "rank": "7", "price_usd": "88.5291", "price_btc": "0.0107433", "24h_volume_usd": "426646000.0", "market_cap_usd": "5094976483.0", "available_supply": "57551432.0", "total_supply": "57551432.0", "max_supply": "84000000.0", "percent_change_1h": "0.97", "percent_change_24h": "6.82", "percent_change_7d": "-0.65", "last_updated": "1532469370", "price_eur": "75.7747021364", "24h_volume_eur": "365179060.531", "market_cap_eur": "4360942621.0"}, {"id": "cardano", "name": "Cardano", "symbol": "ADA", "rank": "8", "price_usd": "0.172256", "price_btc": "0.00002090", "24h_volume_usd": "188613000.0", "market_cap_usd": "4466093463.0", "available_supply": "25927070538.0", "total_supply": "31112483745.0", "max_supply": "45000000000.0", "percent_change_1h": "0.08", "percent_change_24h": "3.05", "percent_change_7d": "1.84", "last_updated": "1532469401", "price_eur": "0.1474390578", "24h_volume_eur": "161439502.876", "market_cap_eur": "3822662851.0"}, {"id": "iota", "name": "IOTA", "symbol": "MIOTA", "rank": "9", "price_usd": "0.973715", "price_btc": "0.00011816", "24h_volume_usd": "45125000.0", "market_cap_usd": "2706470330.0", "available_supply": "2779530283.0", "total_supply": "2779530283.0", "max_supply": "2779530283.0", "percent_change_1h": "0.12", "percent_change_24h": "2.04", "percent_change_7d": "-13.55", "last_updated": "1532469393", "price_eur": "0.8334317653", "24h_volume_eur": "38623835.9354", "market_cap_eur": "2316548830.0"}, {"id": "tether", "name": "Tether", "symbol": "USDT", "rank": "10", "price_usd": "0.996492", "price_btc": "0.00012093", "24h_volume_usd": "4230380000.0", "market_cap_usd": "2498345297.0", "available_supply": "2507140346.0", "total_supply": "3080109502.0", "max_supply": null, "percent_change_1h": "-0.11", "percent_change_24h": "-0.1", "percent_change_7d": "-0.38", "last_updated": "1532469391", "price_eur": "0.8529272802", "24h_volume_eur": "3620908655.16", "market_cap_eur": "2138408396.0"}, {"id": "tron", "name": "TRON", "symbol": "TRX", "rank": "11", "price_usd": "0.0376423", "price_btc": "0.00000457", "24h_volume_usd": "308248000.0", "market_cap_usd": "2474910143.0", "available_supply": "65748111645.0", "total_supply": "99000000000.0", "max_supply": null, "percent_change_1h": "0.15", "percent_change_24h": "9.74", "percent_change_7d": "-4.83", "last_updated": "1532469394", "price_eur": "0.0322191694", "24h_volume_eur": "263838674.336", "market_cap_eur": "2118349547.0"}, {"id": "monero", "name": "Monero", "symbol": "XMR", "rank": "12", "price_usd": "141.648", "price_btc": "0.0171894", "24h_volume_usd": "35119300.0", "market_cap_usd": "2302536844.0", "available_supply": "16255343.0", "total_supply": "16255343.0", "max_supply": null, "percent_change_1h": "0.48", "percent_change_24h": "5.49", "percent_change_7d": "-1.7", "last_updated": "1532469398", "price_eur": "121.240755957", "24h_volume_eur": "30059658.3128", "market_cap_eur": "1970810090.0"}, {"id": "neo", "name": "NEO", "symbol": "NEO", "rank": "13", "price_usd": "33.7943", "price_btc": "0.00410105", "24h_volume_usd": "116654000.0", "market_cap_usd": "2196629500.0", "available_supply": "65000000.0", "total_supply": "100000000.0", "max_supply": "100000000.0", "percent_change_1h": "-0.5", "percent_change_24h": "3.99", "percent_change_7d": "-13.56", "last_updated": "1532469390", "price_eur": "28.9255512188", "24h_volume_eur": "99847644.481", "market_cap_eur": "1880160829.0"}, {"id": "dash", "name": "Dash", "symbol": "DASH", "rank": "14", "price_usd": "250.378", "price_btc": "0.0303842", "24h_volume_usd": "99693500.0", "market_cap_usd": "2056353600.0", "available_supply": "8212996.0", "total_supply": "8212996.0", "max_supply": "18900000.0", "percent_change_1h": "0.41", "percent_change_24h": "3.55", "percent_change_7d": "-3.55", "last_updated": "1532469383", "price_eur": "214.306012052", "24h_volume_eur": "85330645.7135", "market_cap_eur": "1760094495.0"}, {"id": "ethereum-classic", "name": "Ethereum Classic", "symbol": "ETC", "rank": "15", "price_usd": "16.5095", "price_btc": "0.00200348", "24h_volume_usd": "211217000.0", "market_cap_usd": "1704853352.0", "available_supply": "103264990.0", "total_supply": "103264990.0", "max_supply": null, "percent_change_1h": "0.25", "percent_change_24h": "2.68", "percent_change_7d": "-7.61", "last_updated": "1532469388", "price_eur": "14.1309743906", "24h_volume_eur": "180786941.934", "market_cap_eur": "1459234929.0"}, {"id": "nem", "name": "NEM", "symbol": "XEM", "rank": "16", "price_usd": "0.177121", "price_btc": "0.00002149", "24h_volume_usd": "13515100.0", "market_cap_usd": "1594089000.0", "available_supply": "8999999999.0", "total_supply": "8999999999.0", "max_supply": null, "percent_change_1h": "0.18", "percent_change_24h": "0.91", "percent_change_7d": "-5.08", "last_updated": "1532469388", "price_eur": "0.1516031567", "24h_volume_eur": "11567977.9512", "market_cap_eur": "1364428410.0"}, {"id": "tezos", "name": "Tezos", "symbol": "XTZ", "rank": "17", "price_usd": "2.13942", "price_btc": "0.00025962", "24h_volume_usd": "3782060.0", "market_cap_usd": "1299674204.0", "available_supply": "607489041.0", "total_supply": "763306930.0", "max_supply": null, "percent_change_1h": "0.04", "percent_change_24h": "-3.37", "percent_change_7d": "-9.36", "last_updated": "1532469397", "price_eur": "1.8311935086", "24h_volume_eur": "3237178.17036", "market_cap_eur": "1112429988.0"}, {"id": "binance-coin", "name": "Binance Coin", "symbol": "BNB", "rank": "18", "price_usd": "12.0992", "price_btc": "0.00146827", "24h_volume_usd": "45952300.0", "market_cap_usd": "1155625120.0", "available_supply": "95512523.0", "total_supply": "192443301.0", "max_supply": null, "percent_change_1h": "-0.75", "percent_change_24h": "0.85", "percent_change_7d": "-11.31", "last_updated": "1532469394", "price_eur": "10.356066831", "24h_volume_eur": "39331946.7269", "market_cap_eur": "989134073.0"}, {"id": "vechain", "name": "VeChain", "symbol": "VEN", "rank": "19", "price_usd": "1.93252", "price_btc": "0.00023452", "24h_volume_usd": "10414000.0", "market_cap_usd": "1071673840.0", "available_supply": "554547348.0", "total_supply": "873378637.0", "max_supply": null, "percent_change_1h": "0.26", "percent_change_24h": "4.61", "percent_change_7d": "-2.22", "last_updated": "1532469395", "price_eur": "1.654101616", "24h_volume_eur": "8913653.79348", "market_cap_eur": "917277664.0"}, {"id": "omisego", "name": "OmiseGO", "symbol": "OMG", "rank": "20", "price_usd": "7.15711", "price_btc": "0.00086854", "24h_volume_usd": "54082500.0", "market_cap_usd": "1003751742.0", "available_supply": "140245398.0", "total_supply": "140245398.0", "max_supply": null, "percent_change_1h": "1.29", "percent_change_24h": "4.47", "percent_change_7d": "-8.24", "last_updated": "1532469392", "price_eur": "6.1259843194", "24h_volume_eur": "46290827.8554", "market_cap_eur": "859141111.0"}, {"id": "zcash", "name": "Zcash", "symbol": "ZEC", "rank": "21", "price_usd": "219.447", "price_btc": "0.0266306", "24h_volume_usd": "158997000.0", "market_cap_usd": "971158584.0", "available_supply": "4425481.0", "total_supply": "4425481.0", "max_supply": null, "percent_change_1h": "0.69", "percent_change_24h": "12.64", "percent_change_7d": "5.83", "last_updated": "1532469388", "price_eur": "187.831244864", "24h_volume_eur": "136090283.484", "market_cap_eur": "831243652.0"}, {"id": "qtum", "name": "Qtum", "symbol": "QTUM", "rank": "22", "price_usd": "8.10609", "price_btc": "0.0009837", "24h_volume_usd": "208874000.0", "market_cap_usd": "718722547.0", "available_supply": "88664516.0", "total_supply": "100664516.0", "max_supply": null, "percent_change_1h": "-0.36", "percent_change_24h": "3.84", "percent_change_7d": "-7.57", "last_updated": "1532469393", "price_eur": "6.938244659", "24h_volume_eur": "178781498.22", "market_cap_eur": "615176105.0"}, {"id": "0x", "name": "0x", "symbol": "ZRX", "rank": "23", "price_usd": "1.11539", "price_btc": "0.00013536", "24h_volume_usd": "29553100.0", "market_cap_usd": "598628583.0", "available_supply": "536698897.0", "total_supply": "1000000000.0", "max_supply": null, "percent_change_1h": "-0.64", "percent_change_24h": "-0.83", "percent_change_7d": "-10.8", "last_updated": "1532469394", "price_eur": "0.9546956313", "24h_volume_eur": "25295381.4024", "market_cap_eur": "512384093.0"}, {"id": "bytecoin-bcn", "name": "Bytecoin", "symbol": "BCN", "rank": "24", "price_usd": "0.00306365", "price_btc": "0.00000037", "24h_volume_usd": "8851670.0", "market_cap_usd": "563376073.0", "available_supply": "183890481254", "total_supply": "183890481254", "max_supply": "184470000000", "percent_change_1h": "0.08", "percent_change_24h": "0.47", "percent_change_7d": "-11.62", "last_updated": "1532469386", "price_eur": "0.0026222696", "24h_volume_eur": "7576408.86059", "market_cap_eur": "482210416.0"}, {"id": "bitshares", "name": "BitShares", "symbol": "BTS", "rank": "25", "price_usd": "0.209245", "price_btc": "0.00002539", "24h_volume_usd": "15110700.0", "market_cap_usd": "553342125.0", "available_supply": "2644470000.0", "total_supply": "2644470000.0", "max_supply": "3600570502.0", "percent_change_1h": "0.3", "percent_change_24h": "3.77", "percent_change_7d": "-5.16", "last_updated": "1532469388", "price_eur": "0.1790990482", "24h_volume_eur": "12933699.6713", "market_cap_eur": "473622060.0"}, {"id": "decred", "name": "Decred", "symbol": "DCR", "rank": "26", "price_usd": "66.8413", "price_btc": "0.0081114", "24h_volume_usd": "5495400.0", "market_cap_usd": "544819510.0", "available_supply": "8150941.0", "total_supply": "8150941.0", "max_supply": "21000000.0", "percent_change_1h": "0.17", "percent_change_24h": "-2.95", "percent_change_7d": "-11.17", "last_updated": "1532469388", "price_eur": "57.2114660367", "24h_volume_eur": "4703677.07477", "market_cap_eur": "466327299.0"}, {"id": "bitcoin-gold", "name": "Bitcoin Gold", "symbol": "BTG", "rank": "27", "price_usd": "31.6902", "price_btc": "0.0038457", "24h_volume_usd": "23876000.0", "market_cap_usd": "543196128.0", "available_supply": "17140824.0", "total_supply": "17240824.0", "max_supply": "21000000.0", "percent_change_1h": "1.02", "percent_change_24h": "2.51", "percent_change_7d": "1.33", "last_updated": "1532469402", "price_eur": "27.1245891537", "24h_volume_eur": "20436181.868", "market_cap_eur": "464937798.0"}, {"id": "zilliqa", "name": "Zilliqa", "symbol": "ZIL", "rank": "28", "price_usd": "0.0713055", "price_btc": "0.00000865", "24h_volume_usd": "36646200.0", "market_cap_usd": "540224891.0", "available_supply": "7576202268.0", "total_supply": "12600000000.0", "max_supply": null, "percent_change_1h": "-0.09", "percent_change_24h": "2.54", "percent_change_7d": "-13.02", "last_updated": "1532469403", "price_eur": "0.0610325082", "24h_volume_eur": "31366577.65", "market_cap_eur": "462394627.0"}, {"id": "lisk", "name": "Lisk", "symbol": "LSK", "rank": "29", "price_usd": "4.95889", "price_btc": "0.00060178", "24h_volume_usd": "8100850.0", "market_cap_usd": "537187014.0", "available_supply": "108328076.0", "total_supply": "123573724.0", "max_supply": null, "percent_change_1h": "1.02", "percent_change_24h": "2.1", "percent_change_7d": "-12.7", "last_updated": "1532469388", "price_eur": "4.2444621337", "24h_volume_eur": "6933759.58641", "market_cap_eur": "459794418.0"}, {"id": "icon", "name": "ICON", "symbol": "ICX", "rank": "30", "price_usd": "1.30265", "price_btc": "0.00015808", "24h_volume_usd": "28587800.0", "market_cap_usd": "504687435.0", "available_supply": "387431340.0", "total_supply": "800460000.0", "max_supply": null, "percent_change_1h": "0.86", "percent_change_24h": "0.09", "percent_change_7d": "-19.6", "last_updated": "1532469400", "price_eur": "1.1149770611", "24h_volume_eur": "24469152.287", "market_cap_eur": "431977057.0"}, {"id": "digibyte", "name": "DigiByte", "symbol": "DGB", "rank": "31", "price_usd": "0.0476568", "price_btc": "0.00000578", "24h_volume_usd": "9884730.0", "market_cap_usd": "503648240.0", "available_supply": "10568234537.0", "total_supply": "10568234537.0", "max_supply": "21000000000.0", "percent_change_1h": "-0.78", "percent_change_24h": "2.3", "percent_change_7d": "11.33", "last_updated": "1532469380", "price_eur": "0.0407908792", "24h_volume_eur": "8460635.78472", "market_cap_eur": "431087578.0"}, {"id": "ontology", "name": "Ontology", "symbol": "ONT", "rank": "32", "price_usd": "3.2794", "price_btc": "0.00039797", "24h_volume_usd": "37506700.0", "market_cap_usd": "496147558.0", "available_supply": "151292175.0", "total_supply": "1000000000.0", "max_supply": null, "percent_change_1h": "0.55", "percent_change_24h": "2.53", "percent_change_7d": "-15.65", "last_updated": "1532469408", "price_eur": "2.8069364558", "24h_volume_eur": "32103105.3136", "market_cap_eur": "424667521.0"}, {"id": "aeternity", "name": "Aeternity", "symbol": "AE", "rank": "33", "price_usd": "1.96266", "price_btc": "0.00023818", "24h_volume_usd": "8038920.0", "market_cap_usd": "457339960.0", "available_supply": "233020472.0", "total_supply": "273685830.0", "max_supply": null, "percent_change_1h": "-0.06", "percent_change_24h": "2.65", "percent_change_7d": "-1.75", "last_updated": "1532469395", "price_eur": "1.6798993426", "24h_volume_eur": "6880751.84881", "market_cap_eur": "391450938.0"}, {"id": "maker", "name": "Maker", "symbol": "MKR", "rank": "34", "price_usd": "637.841", "price_btc": "0.077404", "24h_volume_usd": "381141.0", "market_cap_usd": "426223069.0", "available_supply": "668228.0", "total_supply": "1000000.0", "max_supply": null, "percent_change_1h": "0.33", "percent_change_24h": "4.15", "percent_change_7d": "-3.0", "last_updated": "1532469391", "price_eur": "545.947172008", "24h_volume_eur": "326229.971241", "market_cap_eur": "364817061.0"}, {"id": "dogecoin", "name": "Dogecoin", "symbol": "DOGE", "rank": "35", "price_usd": "0.00358126", "price_btc": "0.00000043", "24h_volume_usd": "10337400.0", "market_cap_usd": "413348224.0", "available_supply": "115419775188", "total_supply": "115419775188", "max_supply": null, "percent_change_1h": "-0.03", "percent_change_24h": "4.02", "percent_change_7d": "13.19", "last_updated": "1532469381", "price_eur": "0.0030653075", "24h_volume_eur": "8848089.5645", "market_cap_eur": "353797097.0"}, {"id": "siacoin", "name": "Siacoin", "symbol": "SC", "rank": "36", "price_usd": "0.0106081", "price_btc": "0.00000129", "24h_volume_usd": "14251300.0", "market_cap_usd": "380383745.0", "available_supply": "35857858190.0", "total_supply": "35857858190.0", "max_supply": null, "percent_change_1h": "0.22", "percent_change_24h": "1.66", "percent_change_7d": "-10.05", "last_updated": "1532469389", "price_eur": "0.0090797898", "24h_volume_eur": "12198113.5305", "market_cap_eur": "325581814.0"}, {"id": "steem", "name": "Steem", "symbol": "STEEM", "rank": "37", "price_usd": "1.42278", "price_btc": "0.00017266", "24h_volume_usd": "3821050.0", "market_cap_usd": "378783428.0", "available_supply": "266227687.0", "total_supply": "283201781.0", "max_supply": null, "percent_change_1h": "0.19", "percent_change_24h": "5.0", "percent_change_7d": "-9.09", "last_updated": "1532469387", "price_eur": "1.2177999178", "24h_volume_eur": "3270550.87647", "market_cap_eur": "324212055.0"}, {"id": "bytom", "name": "Bytom", "symbol": "BTM", "rank": "38", "price_usd": "0.36688", "price_btc": "0.00004452", "24h_volume_usd": "96675200.0", "market_cap_usd": "367796934.0", "available_supply": "1002499275.0", "total_supply": "1407000000.0", "max_supply": null, "percent_change_1h": "0.73", "percent_change_24h": "4.98", "percent_change_7d": "5.9", "last_updated": "1532469396", "price_eur": "0.3140235552", "24h_volume_eur": "82747192.55", "market_cap_eur": "314808386.0"}, {"id": "verge", "name": "Verge", "symbol": "XVG", "rank": "39", "price_usd": "0.0233396", "price_btc": "0.00000283", "24h_volume_usd": "9996110.0", "market_cap_usd": "354110420.0", "available_supply": "15172086051.0", "total_supply": "15172086051.0", "max_supply": "16555000000.0", "percent_change_1h": "-0.34", "percent_change_24h": "1.82", "percent_change_7d": "-10.75", "last_updated": "1532469388", "price_eur": "0.0199770611", "24h_volume_eur": "8555969.255", "market_cap_eur": "303093690.0"}, {"id": "basic-attention-token", "name": "Basic Attention Token", "symbol": "BAT", "rank": "40", "price_usd": "0.347251", "price_btc": "0.00004214", "24h_volume_usd": "42911800.0", "market_cap_usd": "347251000.0", "available_supply": "1000000000.0", "total_supply": "1500000000.0", "max_supply": null, "percent_change_1h": "0.24", "percent_change_24h": "0.5", "percent_change_7d": "-5.35", "last_updated": "1532469392", "price_eur": "0.2972225075", "24h_volume_eur": "36729491.92", "market_cap_eur": "297222508.0"}, {"id": "bitcoin-diamond", "name": "Bitcoin Diamond", "symbol": "BCD", "rank": "41", "price_usd": "2.23484", "price_btc": "0.0002712", "24h_volume_usd": "5126370.0", "market_cap_usd": "343622015.0", "available_supply": "153756875.0", "total_supply": "156756875.0", "max_supply": "210000000.0", "percent_change_1h": "0.13", "percent_change_24h": "1.88", "percent_change_7d": "1.68", "last_updated": "1532469400", "price_eur": "1.912866338", "24h_volume_eur": "4387813.27034", "market_cap_eur": "294116350.0"}, {"id": "augur", "name": "Augur", "symbol": "REP", "rank": "42", "price_usd": "30.4641", "price_btc": "0.00369692", "24h_volume_usd": "29488200.0", "market_cap_usd": "335105100.0", "available_supply": "11000000.0", "total_supply": "11000000.0", "max_supply": null, "percent_change_1h": "-0.17", "percent_change_24h": "-5.41", "percent_change_7d": "-3.35", "last_updated": "1532469390", "price_eur": "26.0751335251", "24h_volume_eur": "25239831.553", "market_cap_eur": "286826469.0"}, {"id": "nano", "name": "Nano", "symbol": "NANO", "rank": "43", "price_usd": "2.31284", "price_btc": "0.00028067", "24h_volume_usd": "6229920.0", "market_cap_usd": "308181973.0", "available_supply": "133248289.0", "total_supply": "133248289.0", "max_supply": "133248290.0", "percent_change_1h": "0.48", "percent_change_24h": "2.21", "percent_change_7d": "-21.13", "last_updated": "1532469395", "price_eur": "1.9796288688", "24h_volume_eur": "5332374.69187", "market_cap_eur": "263782160.0"}, {"id": "mithril", "name": "Mithril", "symbol": "MITH", "rank": "44", "price_usd": "0.848394", "price_btc": "0.00010296", "24h_volume_usd": "194245000.0", "market_cap_usd": "302533214.0", "available_supply": "356595183.0", "total_supply": "1000000000.0", "max_supply": null, "percent_change_1h": "-0.35", "percent_change_24h": "18.36", "percent_change_7d": "36.13", "last_updated": "1532469408", "price_eur": "0.7261657765", "24h_volume_eur": "166260099.973", "market_cap_eur": "258947218.0"}, {"id": "golem-network-tokens", "name": "Golem", "symbol": "GNT", "rank": "45", "price_usd": "0.303129", "price_btc": "0.00003679", "24h_volume_usd": "5105790.0", "market_cap_usd": "290774068.0", "available_supply": "959242000.0", "total_supply": "1000000000.0", "max_supply": null, "percent_change_1h": "0.93", "percent_change_24h": "1.88", "percent_change_7d": "-8.15", "last_updated": "1532469393", "price_eur": "0.2594571693", "24h_volume_eur": "4370198.23336", "market_cap_eur": "248882214.0"}, {"id": "waves", "name": "Waves", "symbol": "WAVES", "rank": "46", "price_usd": "2.6974", "price_btc": "0.00032734", "24h_volume_usd": "16045400.0", "market_cap_usd": "269740000.0", "available_supply": "100000000.0", "total_supply": "100000000.0", "max_supply": null, "percent_change_1h": "0.24", "percent_change_24h": "-0.85", "percent_change_7d": "-13.23", "last_updated": "1532469390", "price_eur": "2.3087852643", "24h_volume_eur": "13733737.3322", "market_cap_eur": "230878526.0"}, {"id": "stratis", "name": "Stratis", "symbol": "STRAT", "rank": "47", "price_usd": "2.71394", "price_btc": "0.00032934", "24h_volume_usd": "5205280.0", "market_cap_usd": "268536328.0", "available_supply": "98947039.0", "total_supply": "98947039.0", "max_supply": null, "percent_change_1h": "1.11", "percent_change_24h": "-1.28", "percent_change_7d": "-11.43", "last_updated": "1532469389", "price_eur": "2.3229423446", "24h_volume_eur": "4455354.69734", "market_cap_eur": "229848267.0"}, {"id": "rchain", "name": "RChain", "symbol": "RHOC", "rank": "48", "price_usd": "0.736504", "price_btc": "0.00008938", "24h_volume_usd": "380800.0", "market_cap_usd": "265845698.0", "available_supply": "360956217.0", "total_supply": "870663574.0", "max_supply": "1000000000.0", "percent_change_1h": "0.31", "percent_change_24h": "-0.11", "percent_change_7d": "-1.14", "last_updated": "1532469396", "price_eur": "0.630395782", "24h_volume_eur": "325938.099151", "market_cap_eur": "227545277.0"}, {"id": "pundi-x", "name": "Pundi X", "symbol": "NPXS", "rank": "49", "price_usd": "0.00296069", "price_btc": "0.00000036", "24h_volume_usd": "9922370.0", "market_cap_usd": "259022317.0", "available_supply": "87487145429.0", "total_supply": "280755195000", "max_supply": null, "percent_change_1h": "1.2", "percent_change_24h": "0.96", "percent_change_7d": "-25.01", "last_updated": "1532469406", "price_eur": "0.002534143", "24h_volume_eur": "8492852.98548", "market_cap_eur": "221704941.0"}, {"id": "hshare", "name": "Hshare", "symbol": "HSR", "rank": "50", "price_usd": "5.75841", "price_btc": "0.0006988", "24h_volume_usd": "58506800.0", "market_cap_usd": "249174398.0", "available_supply": "43271389.0", "total_supply": "43271389.0", "max_supply": "84000000.0", "percent_change_1h": "-0.31", "percent_change_24h": "1.42", "percent_change_7d": "3.83", "last_updated": "1532469395", "price_eur": "4.9287951931", "24h_volume_eur": "50077718.4333", "market_cap_eur": "213275813.0"}, {"id": "status", "name": "Status", "symbol": "SNT", "rank": "51", "price_usd": "0.0712097", "price_btc": "0.00000864", "24h_volume_usd": "12483500.0", "market_cap_usd": "247132109.0", "available_supply": "3470483788.0", "total_supply": "6804870174.0", "max_supply": null, "percent_change_1h": "0.83", "percent_change_24h": "2.98", "percent_change_7d": "-10.13", "last_updated": "1532469391", "price_eur": "0.0609505101", "24h_volume_eur": "10685000.6847", "market_cap_eur": "211527757.0"}, {"id": "kucoin-shares", "name": "KuCoin Shares", "symbol": "KCS", "rank": "52", "price_usd": "2.72199", "price_btc": "0.00033032", "24h_volume_usd": "562827.0", "market_cap_usd": "246967721.0", "available_supply": "90730576.0", "total_supply": "180730576.0", "max_supply": null, "percent_change_1h": "0.16", "percent_change_24h": "0.29", "percent_change_7d": "-13.84", "last_updated": "1532469399", "price_eur": "2.3298325801", "24h_volume_eur": "481740.447823", "market_cap_eur": "211387052.0"}, {"id": "waltonchain", "name": "Waltonchain", "symbol": "WTC", "rank": "53", "price_usd": "5.82882", "price_btc": "0.00070734", "24h_volume_usd": "7049390.0", "market_cap_usd": "233992730.0", "available_supply": "40144099.0", "total_supply": "70000000.0", "max_supply": "100000000.0", "percent_change_1h": "1.05", "percent_change_24h": "-0.07", "percent_change_7d": "-21.39", "last_updated": "1532469398", "price_eur": "4.9890612161", "24h_volume_eur": "6033783.55245", "market_cap_eur": "200281369.0"}, {"id": "wanchain", "name": "Wanchain", "symbol": "WAN", "rank": "54", "price_usd": "2.03431", "price_btc": "0.00024687", "24h_volume_usd": "6891720.0", "market_cap_usd": "215947077.0", "available_supply": "106152493.0", "total_supply": "210000000.0", "max_supply": null, "percent_change_1h": "-0.32", "percent_change_24h": "0.42", "percent_change_7d": "-22.11", "last_updated": "1532469404", "price_eur": "1.7412267187", "24h_volume_eur": "5898829.08792", "market_cap_eur": "184835556.0"}, {"id": "populous", "name": "Populous", "symbol": "PPT", "rank": "55", "price_usd": "5.81623", "price_btc": "0.00070582", "24h_volume_usd": "6946060.0", "market_cap_usd": "215223931.0", "available_supply": "37004027.0", "total_supply": "53252246.0", "max_supply": "53252246.0", "percent_change_1h": "0.21", "percent_change_24h": "-2.84", "percent_change_7d": "-19.99", "last_updated": "1532469395", "price_eur": "4.9782850589", "24h_volume_eur": "5945340.31772", "market_cap_eur": "184216594.0"}, {"id": "maidsafecoin", "name": "MaidSafeCoin", "symbol": "MAID", "rank": "56", "price_usd": "0.474042", "price_btc": "0.00005753", "24h_volume_usd": "1947550.0", "market_cap_usd": "214528850.0", "available_supply": "452552412.0", "total_supply": "452552412.0", "max_supply": null, "percent_change_1h": "0.27", "percent_change_24h": "10.47", "percent_change_7d": "16.34", "last_updated": "1532469384", "price_eur": "0.4057467132", "24h_volume_eur": "1666966.24213", "market_cap_eur": "183621654.0"}, {"id": "iostoken", "name": "IOST", "symbol": "IOST", "rank": "57", "price_usd": "0.0251326", "price_btc": "0.00000305", "24h_volume_usd": "23453100.0", "market_cap_usd": "211113840.0", "available_supply": "8400000000.0", "total_supply": "21000000000.0", "max_supply": null, "percent_change_1h": "-0.01", "percent_change_24h": "10.26", "percent_change_7d": "-0.66", "last_updated": "1532469402", "price_eur": "0.0215117434", "24h_volume_eur": "20074209.1208", "market_cap_eur": "180698644.0"}, {"id": "mixin", "name": "Mixin", "symbol": "XIN", "rank": "58", "price_usd": "465.093", "price_btc": "0.0564405", "24h_volume_usd": "120488.0", "market_cap_usd": "204246944.0", "available_supply": "439153.0", "total_supply": "1000000.0", "max_supply": null, "percent_change_1h": "0.32", "percent_change_24h": "-3.66", "percent_change_7d": "-15.03", "last_updated": "1532469400", "price_eur": "398.086996713", "24h_volume_eur": "103129.279649", "market_cap_eur": "174821062.0"}, {"id": "digixdao", "name": "DigixDAO", "symbol": "DGD", "rank": "59", "price_usd": "97.4939", "price_btc": "0.0118312", "24h_volume_usd": "504687.0", "market_cap_usd": "194987800.0", "available_supply": "2000000.0", "total_supply": "2000000.0", "max_supply": null, "percent_change_1h": "0.08", "percent_change_24h": "0.74", "percent_change_7d": "-8.89", "last_updated": "1532469389", "price_eur": "83.4479423446", "24h_volume_eur": "431976.68447", "market_cap_eur": "166895885.0"}, {"id": "gxchain", "name": "GXChain", "symbol": "GXS", "rank": "60", "price_usd": "3.08336", "price_btc": "0.00037417", "24h_volume_usd": "5876340.0", "market_cap_usd": "185001600.0", "available_supply": "60000000.0", "total_supply": "100000000.0", "max_supply": "100000000.0", "percent_change_1h": "-4.32", "percent_change_24h": "-10.13", "percent_change_7d": "3.06", "last_updated": "1532469396", "price_eur": "2.6391399617", "24h_volume_eur": "5029735.00411", "market_cap_eur": "158348398.0"}, {"id": "ardor", "name": "Ardor", "symbol": "ARDR", "rank": "61", "price_usd": "0.180614", "price_btc": "0.00002192", "24h_volume_usd": "5365190.0", "market_cap_usd": "180433295.0", "available_supply": "998999495.0", "total_supply": "998999495.0", "max_supply": "998999495.0", "percent_change_1h": "0.27", "percent_change_24h": "4.11", "percent_change_7d": "3.51", "last_updated": "1532469388", "price_eur": "0.1545929197", "24h_volume_eur": "4592226.44481", "market_cap_eur": "154438249.0"}, {"id": "bitcoin-private", "name": "Bitcoin Private", "symbol": "BTCP", "rank": "62", "price_usd": "8.73269", "price_btc": "0.00105974", "24h_volume_usd": "737260.0", "market_cap_usd": "178994089.0", "available_supply": "20497016.0", "total_supply": "20497016.0", "max_supply": "21000000.0", "percent_change_1h": "1.07", "percent_change_24h": "15.67", "percent_change_7d": "3.54", "last_updated": "1532469402", "price_eur": "7.4745703232", "24h_volume_eur": "631042.864969", "market_cap_eur": "153206389.0"}, {"id": "huobi-token", "name": "Huobi Token", "symbol": "HT", "rank": "63", "price_usd": "3.38188", "price_btc": "0.0004104", "24h_volume_usd": "53283700.0", "market_cap_usd": "169094676.0", "available_supply": "50000200.0", "total_supply": "500000000.0", "max_supply": null, "percent_change_1h": "-0.42", "percent_change_24h": "-0.21", "percent_change_7d": "-7.41", "last_updated": "1532469402", "price_eur": "2.8946521501", "24h_volume_eur": "45607111.0655", "market_cap_eur": "144733186.0"}, {"id": "moac", "name": "MOAC", "symbol": "MOAC", "rank": "64", "price_usd": "4.58697", "price_btc": "0.00055664", "24h_volume_usd": "680480.0", "market_cap_usd": "164658712.0", "available_supply": "35897055.0", "total_supply": "56483386.0", "max_supply": null, "percent_change_1h": "-0.08", "percent_change_24h": "-0.11", "percent_change_7d": "4.23", "last_updated": "1532469405", "price_eur": "3.9261246919", "24h_volume_eur": "582443.166256", "market_cap_eur": "140936312.0"}, {"id": "komodo", "name": "Komodo", "symbol": "KMD", "rank": "65", "price_usd": "1.51197", "price_btc": "0.00018348", "24h_volume_usd": "1225250.0", "market_cap_usd": "164067418.0", "available_supply": "108512350.0", "total_supply": "108512350.0", "max_supply": null, "percent_change_1h": "-0.34", "percent_change_24h": "2.0", "percent_change_7d": "-11.92", "last_updated": "1532469393", "price_eur": "1.294140304", "24h_volume_eur": "1048728.0882", "market_cap_eur": "140430206.0"}, {"id": "aelf", "name": "aelf", "symbol": "ELF", "rank": "66", "price_usd": "0.647775", "price_btc": "0.00007861", "24h_volume_usd": "15914900.0", "market_cap_usd": "161943750.0", "available_supply": "250000000.0", "total_supply": "280000000.0", "max_supply": "1000000000.0", "percent_change_1h": "0.16", "percent_change_24h": "7.14", "percent_change_7d": "-9.72", "last_updated": "1532469403", "price_eur": "0.5544499795", "24h_volume_eur": "13622038.4826", "market_cap_eur": "138612495.0"}, {"id": "loopring", "name": "Loopring", "symbol": "LRC", "rank": "67", "price_usd": "0.281577", "price_btc": "0.00003417", "24h_volume_usd": "4698240.0", "market_cap_usd": "161082893.0", "available_supply": "572074043.0", "total_supply": "1374956262.0", "max_supply": null, "percent_change_1h": "0.42", "percent_change_24h": "7.05", "percent_change_7d": "-12.55", "last_updated": "1532469397", "price_eur": "0.2410101684", "24h_volume_eur": "4021364.00986", "market_cap_eur": "137875662.0"}, {"id": "aion", "name": "Aion", "symbol": "AION", "rank": "68", "price_usd": "0.845088", "price_btc": "0.00010255", "24h_volume_usd": "4403740.0", "market_cap_usd": "159526646.0", "available_supply": "188769272.0", "total_supply": "465934587.0", "max_supply": null, "percent_change_1h": "2.02", "percent_change_24h": "0.31", "percent_change_7d": "-23.34", "last_updated": "1532469398", "price_eur": "0.7233360723", "24h_volume_eur": "3769292.65955", "market_cap_eur": "136543624.0"}, {"id": "nebulas-token", "name": "Nebulas", "symbol": "NAS", "rank": "69", "price_usd": "3.37354", "price_btc": "0.00040939", "24h_volume_usd": "20430300.0", "market_cap_usd": "153496070.0", "available_supply": "45500000.0", "total_supply": "100000000.0", "max_supply": "100000000.0", "percent_change_1h": "0.32", "percent_change_24h": "1.68", "percent_change_7d": "-10.11", "last_updated": "1532469395", "price_eur": "2.8875136949", "24h_volume_eur": "17486904.2728", "market_cap_eur": "131381873.0"}, {"id": "kin", "name": "Kin", "symbol": "KIN", "rank": "70", "price_usd": "0.00020024", "price_btc": "0.00000002", "24h_volume_usd": "3703030.0", "market_cap_usd": "151400976.0", "available_supply": "756097560976", "total_supply": "10000000000000", "max_supply": null, "percent_change_1h": "0.04", "percent_change_24h": "1.71", "percent_change_7d": "22.98", "last_updated": "1532469394", "price_eur": "0.0001713914", "24h_volume_eur": "3169534.03177", "market_cap_eur": "129588619.0"}, {"id": "cryptonex", "name": "Cryptonex", "symbol": "CNX", "rank": "71", "price_usd": "3.03259", "price_btc": "0.00036801", "24h_volume_usd": "4569350.0", "market_cap_usd": "137636453.0", "available_supply": "45385777.0", "total_supply": "106823403.0", "max_supply": "210000000.0", "percent_change_1h": "0.75", "percent_change_24h": "7.81", "percent_change_7d": "15.66", "last_updated": "1532469398", "price_eur": "2.5956844015", "24h_volume_eur": "3911043.20734", "market_cap_eur": "117807153.0"}, {"id": "decentraland", "name": "Decentraland", "symbol": "MANA", "rank": "72", "price_usd": "0.128752", "price_btc": "0.00001562", "24h_volume_usd": "10927900.0", "market_cap_usd": "135207820.0", "available_supply": "1050141509.0", "total_supply": "2644403343.0", "max_supply": null, "percent_change_1h": "1.64", "percent_change_24h": "-0.88", "percent_change_7d": "3.0", "last_updated": "1532469397", "price_eur": "0.1102026842", "24h_volume_eur": "9353516.15996", "market_cap_eur": "115728413.0"}, {"id": "monacoin", "name": "MonaCoin", "symbol": "MONA", "rank": "73", "price_usd": "2.20578", "price_btc": "0.00026768", "24h_volume_usd": "803617.0", "market_cap_usd": "134734060.0", "available_supply": "61082275.0", "total_supply": "61082275.0", "max_supply": null, "percent_change_1h": "-0.29", "percent_change_24h": "0.81", "percent_change_7d": "-4.04", "last_updated": "1532469389", "price_eur": "1.8879930156", "24h_volume_eur": "687839.804163", "market_cap_eur": "115322908.0"}, {"id": "emercoin", "name": "Emercoin", "symbol": "EMC", "rank": "74", "price_usd": "3.20233", "price_btc": "0.00038861", "24h_volume_usd": "2272450.0", "market_cap_usd": "134698788.0", "available_supply": "42062744.0", "total_supply": "42062744.0", "max_supply": null, "percent_change_1h": "0.42", "percent_change_24h": "7.26", "percent_change_7d": "5.57", "last_updated": "1532469388", "price_eur": "2.7409699397", "24h_volume_eur": "1945057.86086", "market_cap_eur": "115292718.0"}, {"id": "funfair", "name": "FunFair", "symbol": "FUN", "rank": "75", "price_usd": "0.0263613", "price_btc": "0.00000320", "24h_volume_usd": "1505400.0", "market_cap_usd": "132092472.0", "available_supply": "5010848189.0", "total_supply": "10999873621.0", "max_supply": null, "percent_change_1h": "0.16", "percent_change_24h": "5.96", "percent_change_7d": "-7.52", "last_updated": "1532469393", "price_eur": "0.0225634244", "24h_volume_eur": "1288516.8447", "market_cap_eur": "113061894.0"}, {"id": "zencash", "name": "ZenCash", "symbol": "ZEN", "rank": "76", "price_usd": "30.2793", "price_btc": "0.00367449", "24h_volume_usd": "6599960.0", "market_cap_usd": "131616547.0", "available_supply": "4346750.0", "total_supply": "4346750.0", "max_supply": "21000000.0", "percent_change_1h": "1.0", "percent_change_24h": "19.03", "percent_change_7d": "18.53", "last_updated": "1532469394", "price_eur": "25.9169576828", "24h_volume_eur": "5649102.98548", "market_cap_eur": "112654536.0"}, {"id": "reddcoin", "name": "ReddCoin", "symbol": "RDD", "rank": "77", "price_usd": "0.00453283", "price_btc": "0.00000055", "24h_volume_usd": "4940490.0", "market_cap_usd": "130584999.0", "available_supply": "28808713174.0", "total_supply": "28808713174.0", "max_supply": null, "percent_change_1h": "-1.1", "percent_change_24h": "3.0", "percent_change_7d": "-3.28", "last_updated": "1532469381", "price_eur": "0.0038797846", "24h_volume_eur": "4228713.02383", "market_cap_eur": "111771603.0"}, {"id": "ark", "name": "Ark", "symbol": "ARK", "rank": "78", "price_usd": "1.24476", "price_btc": "0.00015106", "24h_volume_usd": "3129380.0", "market_cap_usd": "129525297.0", "available_supply": "104056442.0", "total_supply": "135306442.0", "max_supply": null, "percent_change_1h": "-0.66", "percent_change_24h": "-2.24", "percent_change_7d": "-18.19", "last_updated": "1532469392", "price_eur": "1.0654272802", "24h_volume_eur": "2678529.85483", "market_cap_eur": "110864572.0"}, {"id": "wax", "name": "WAX", "symbol": "WAX", "rank": "79", "price_usd": "0.1349", "price_btc": "0.00001637", "24h_volume_usd": "1829410.0", "market_cap_usd": "125571906.0", "available_supply": "930851783.0", "total_supply": "1850000000.0", "max_supply": null, "percent_change_1h": "0.08", "percent_change_24h": "-0.87", "percent_change_7d": "-13.02", "last_updated": "1532469399", "price_eur": "0.1154649411", "24h_volume_eur": "1565846.68584", "market_cap_eur": "107480746.0"}, {"id": "dentacoin", "name": "Dentacoin", "symbol": "DCN", "rank": "80", "price_usd": "0.00038494", "price_btc": "0.00000005", "24h_volume_usd": "78395.3", "market_cap_usd": "125192732.0", "available_supply": "325226613094", "total_supply": "1963173416169", "max_supply": "8000000000000", "percent_change_1h": "-0.65", "percent_change_24h": "8.8", "percent_change_7d": "-1.39", "last_updated": "1532469395", "price_eur": "0.0003294816", "24h_volume_eur": "67100.8798959", "market_cap_eur": "107156201.0"}, {"id": "power-ledger", "name": "Power Ledger", "symbol": "POWR", "rank": "81", "price_usd": "0.33427", "price_btc": "0.00004056", "24h_volume_usd": "21602600.0", "market_cap_usd": "124926930.0", "available_supply": "373730607.0", "total_supply": "1000000000.0", "max_supply": null, "percent_change_1h": "0.32", "percent_change_24h": "1.24", "percent_change_7d": "-14.82", "last_updated": "1532469399", "price_eur": "0.2861116817", "24h_volume_eur": "18490310.8737", "market_cap_eur": "106928692.0"}, {"id": "kyber-network", "name": "Kyber Network", "symbol": "KNC", "rank": "82", "price_usd": "0.910786", "price_btc": "0.00011053", "24h_volume_usd": "4540930.0", "market_cap_usd": "122166183.0", "available_supply": "134132697.0", "total_supply": "215625349.0", "max_supply": null, "percent_change_1h": "0.1", "percent_change_24h": "-0.88", "percent_change_7d": "-9.39", "last_updated": "1532469397", "price_eur": "0.7795689537", "24h_volume_eur": "3886717.68009", "market_cap_eur": "104565686.0"}, {"id": "holo", "name": "Holo", "symbol": "HOT", "rank": "83", "price_usd": "0.000901952", "price_btc": "0.00000011", "24h_volume_usd": "44958400.0", "market_cap_usd": "120153152.0", "available_supply": "133214575156", "total_supply": "177619433541", "max_supply": null, "percent_change_1h": "2.84", "percent_change_24h": "-3.24", "percent_change_7d": "99.66", "last_updated": "1532469409", "price_eur": "0.0007720077", "24h_volume_eur": "38481238.017", "market_cap_eur": "102842674.0"}, {"id": "monaco", "name": "MCO", "symbol": "MCO", "rank": "84", "price_usd": "7.48727", "price_btc": "0.0009086", "24h_volume_usd": "10061700.0", "market_cap_usd": "118252678.0", "available_supply": "15793831.0", "total_supply": "31587682.0", "max_supply": null, "percent_change_1h": "0.22", "percent_change_24h": "-0.58", "percent_change_7d": "-8.27", "last_updated": "1532469394", "price_eur": "6.4085781293", "24h_volume_eur": "8612109.69597", "market_cap_eur": "101216001.0"}, {"id": "bancor", "name": "Bancor", "symbol": "BNT", "rank": "85", "price_usd": "2.30241", "price_btc": "0.0002794", "24h_volume_usd": "11219200.0", "market_cap_usd": "118025097.0", "available_supply": "51261546.0", "total_supply": "75915368.0", "max_supply": null, "percent_change_1h": "0.06", "percent_change_24h": "4.36", "percent_change_7d": "-4.07", "last_updated": "1532469400", "price_eur": "1.9707015201", "24h_volume_eur": "9602848.53465", "market_cap_eur": "101021207.0"}, {"id": "dropil", "name": "Dropil", "symbol": "DROP", "rank": "86", "price_usd": "0.00585266", "price_btc": "0.00000071", "24h_volume_usd": "299843.0", "market_cap_usd": "117980267.0", "available_supply": "20158400994.0", "total_supply": "30000000000.0", "max_supply": null, "percent_change_1h": "-1.71", "percent_change_24h": "-2.1", "percent_change_7d": "-0.56", "last_updated": "1532469405", "price_eur": "0.0050094666", "24h_volume_eur": "256644.583676", "market_cap_eur": "100982836.0"}, {"id": "loom-network", "name": "Loom Network", "symbol": "LOOM", "rank": "87", "price_usd": "0.192818", "price_btc": "0.00002340", "24h_volume_usd": "4155320.0", "market_cap_usd": "113180357.0", "available_supply": "586980244.0", "total_supply": "1000000000.0", "max_supply": null, "percent_change_1h": "0.44", "percent_change_24h": "3.69", "percent_change_7d": "-25.12", "last_updated": "1532469405", "price_eur": "0.165038688", "24h_volume_eur": "3556662.5582", "market_cap_eur": "96874449.0"}, {"id": "paypex", "name": "Paypex", "symbol": "PAYX", "rank": "88", "price_usd": "1.61822", "price_btc": "0.00019638", "24h_volume_usd": "45395.3", "market_cap_usd": "110732801.0", "available_supply": "68428768.0", "total_supply": "150000000.0", "max_supply": null, "percent_change_1h": "4.13", "percent_change_24h": "7.17", "percent_change_7d": "1.91", "last_updated": "1532469398", "price_eur": "1.385082854", "24h_volume_eur": "38855.1937825", "market_cap_eur": "94779514.0"}, {"id": "gas", "name": "Gas", "symbol": "GAS", "rank": "89", "price_usd": "10.5803", "price_btc": "0.00128395", "24h_volume_usd": "3826830.0", "market_cap_usd": "107161247.0", "available_supply": "10128375.0", "total_supply": "17190378.0", "max_supply": "100000000.0", "percent_change_1h": "-0.1", "percent_change_24h": "2.56", "percent_change_7d": "-15.92", "last_updated": "1532469397", "price_eur": "9.0559949329", "24h_volume_eur": "3275498.15119", "market_cap_eur": "91722514.0"}, {"id": "nxt", "name": "Nxt", "symbol": "NXT", "rank": "90", "price_usd": "0.105882", "price_btc": "0.00001285", "24h_volume_usd": "2970040.0", "market_cap_usd": "105776112.0", "available_supply": "998999942.0", "total_supply": "998999942.0", "max_supply": "1000000000.0", "percent_change_1h": "-0.55", "percent_change_24h": "3.34", "percent_change_7d": "10.53", "last_updated": "1532469376", "price_eur": "0.0906275678", "24h_volume_eur": "2542145.9874", "market_cap_eur": "90536935.0"}, {"id": "cybermiles", "name": "CyberMiles", "symbol": "CMT", "rank": "91", "price_usd": "0.148459", "price_btc": "0.00001802", "24h_volume_usd": "13114600.0", "market_cap_usd": "102852158.0", "available_supply": "692798400.0", "total_supply": "1000000000.0", "max_supply": null, "percent_change_1h": "-0.2", "percent_change_24h": "3.51", "percent_change_7d": "-14.75", "last_updated": "1532469400", "price_eur": "0.1270704944", "24h_volume_eur": "11225178.0334", "market_cap_eur": "88034235.0"}, {"id": "nuls", "name": "Nuls", "symbol": "NULS", "rank": "92", "price_usd": "2.53722", "price_btc": "0.0003079", "24h_volume_usd": "6362380.0", "market_cap_usd": "101488800.0", "available_supply": "40000000.0", "total_supply": "40000000.0", "max_supply": null, "percent_change_1h": "0.33", "percent_change_24h": "3.26", "percent_change_7d": "-9.67", "last_updated": "1532469395", "price_eur": "2.1716824158", "24h_volume_eur": "5445751.16406", "market_cap_eur": "86867297.0"}, {"id": "pivx", "name": "PIVX", "symbol": "PIVX", "rank": "93", "price_usd": "1.78644", "price_btc": "0.00021679", "24h_volume_usd": "1564860.0", "market_cap_usd": "101436146.0", "available_supply": "56781166.0", "total_supply": "56781166.0", "max_supply": null, "percent_change_1h": "-0.78", "percent_change_24h": "-2.83", "percent_change_7d": "-12.55", "last_updated": "1532469385", "price_eur": "1.5290673788", "24h_volume_eur": "1339410.4355", "market_cap_eur": "86822229.0"}, {"id": "tenx", "name": "TenX", "symbol": "PAY", "rank": "94", "price_usd": "0.910259", "price_btc": "0.00011046", "24h_volume_usd": "8316650.0", "market_cap_usd": "99400611.0", "available_supply": "109200361.0", "total_supply": "205218256.0", "max_supply": null, "percent_change_1h": "-1.0", "percent_change_24h": "-6.32", "percent_change_7d": "-26.46", "last_updated": "1532469393", "price_eur": "0.7791178787", "24h_volume_eur": "7118469.255", "market_cap_eur": "85079953.0"}, {"id": "electroneum", "name": "Electroneum", "symbol": "ETN", "rank": "95", "price_usd": "0.0128631", "price_btc": "0.00000156", "24h_volume_usd": "1067530.0", "market_cap_usd": "96239515.0", "available_supply": "7481828992.0", "total_supply": "7481828992.0", "max_supply": "21000000000.0", "percent_change_1h": "0.89", "percent_change_24h": "-6.37", "percent_change_7d": "4.82", "last_updated": "1532469400", "price_eur": "0.0110099117", "24h_volume_eur": "913730.827171", "market_cap_eur": "82374276.0"}, {"id": "polymath-network", "name": "Polymath", "symbol": "POLY", "rank": "96", "price_usd": "0.347538", "price_btc": "0.00004217", "24h_volume_usd": "3510650.0", "market_cap_usd": "96066491.0", "available_supply": "276420107.0", "total_supply": "1000000000.0", "max_supply": null, "percent_change_1h": "-0.27", "percent_change_24h": "-0.65", "percent_change_7d": "-14.68", "last_updated": "1532469404", "price_eur": "0.2974681594", "24h_volume_eur": "3004870.24103", "market_cap_eur": "82226180.0"}, {"id": "byteball", "name": "Byteball Bytes", "symbol": "GBYTE", "rank": "97", "price_usd": "143.895", "price_btc": "0.0174622", "24h_volume_usd": "96749.1", "market_cap_usd": "95375155.0", "available_supply": "662811.0", "total_supply": "1000000.0", "max_supply": null, "percent_change_1h": "0.27", "percent_change_24h": "6.27", "percent_change_7d": "6.63", "last_updated": "1532469393", "price_eur": "123.164030403", "24h_volume_eur": "82810.4457683", "market_cap_eur": "81634445.0"}, {"id": "veritaseum", "name": "Veritaseum", "symbol": "VERI", "rank": "98", "price_usd": "45.7732", "price_btc": "0.00555472", "24h_volume_usd": "1886130.0", "market_cap_usd": "93223779.0", "available_supply": "2036645.0", "total_supply": "100000000.0", "max_supply": null, "percent_change_1h": "-0.85", "percent_change_24h": "-1.25", "percent_change_7d": "-13.18", "last_updated": "1532469392", "price_eur": "39.178649685", "24h_volume_eur": "1614395.02876", "market_cap_eur": "79793018.0"}, {"id": "smartcash", "name": "SmartCash", "symbol": "SMART", "rank": "99", "price_usd": "0.0879277", "price_btc": "0.00001067", "24h_volume_usd": "2917680.0", "market_cap_usd": "92655841.0", "available_supply": "1053773052.0", "total_supply": "1654817331.0", "max_supply": "5000000000.0", "percent_change_1h": "0.53", "percent_change_24h": "-2.78", "percent_change_7d": "-2.89", "last_updated": "1532469396", "price_eur": "0.0752599459", "24h_volume_eur": "2497329.49877", "market_cap_eur": "79306903.0"}, {"id": "qash", "name": "QASH", "symbol": "QASH", "rank": "100", "price_usd": "0.264606", "price_btc": "0.00003211", "24h_volume_usd": "1503610.0", "market_cap_usd": "92612100.0", "available_supply": "350000000.0", "total_supply": "1000000000.0", "max_supply": null, "percent_change_1h": "0.23", "percent_change_24h": "-1.07", "percent_change_7d": "-10.03", "last_updated": "1532469399", "price_eur": "0.2264841824", "24h_volume_eur": "1286984.73021", "market_cap_eur": "79269464.0"}]